pytrakt-4.2.2.dist-info/licenses/LICENSE
trakt/__init__.py
trakt/__version__.py
trakt/api.py
trakt/calendar.py
trakt/config.py
trakt/core.py
trakt/decorators.py
trakt/errors.py
trakt/mixins.py
trakt/movies.py
trakt/people.py
trakt/sync.py
trakt/tv.py
trakt/users.py
trakt/utils.py
trakt/auth/__init__.py
trakt/auth/base.py
trakt/auth/device.py
trakt/auth/oauth.py
trakt/auth/pin.py
pytrakt-4.2.2.dist-info/METADATA
pytrakt-4.2.2.dist-info/WHEEL
pytrakt-4.2.2.dist-info/top_level.txt
pytrakt-4.2.2.dist-info/RECORD
