Metadata-Version: 2.4
Name: pytrakt
Version: 4.2.2
Summary: Pythonic abstraction layer for easier scripting of the Trakt.tv REST API.
Home-page: https://github.com/glensc/python-pytrakt
Author: Elan Ruusamäe
Author-email: glen@pld-linux.org
License: Apache 2.0
Classifier: Development Status :: 5 - Production/Stable
Classifier: Intended Audience :: Developers
Classifier: Natural Language :: English
Classifier: License :: Freely Distributable
Classifier: Programming Language :: Python
Classifier: Programming Language :: Python :: 3
Classifier: Programming Language :: Python :: 3.6
Classifier: Programming Language :: Python :: 3.7
Classifier: Programming Language :: Python :: 3.8
Classifier: Programming Language :: Python :: 3.9
Classifier: Programming Language :: Python :: 3.10
Classifier: Programming Language :: Python :: 3.11
Classifier: Programming Language :: Python :: 3.12
Classifier: Programming Language :: Python :: 3.13
License-File: LICENSE
Requires-Dist: deprecated~=1.2.13
Requires-Dist: requests-oauthlib>=1.3
Requires-Dist: requests>=2.25
Requires-Dist: dataclasses; python_version < "3.7"
Dynamic: author
Dynamic: author-email
Dynamic: classifier
Dynamic: description
Dynamic: home-page
Dynamic: license
Dynamic: license-file
Dynamic: requires-dist
Dynamic: summary
